cariuska/__init__.py
cariuska/calc.py
cariuska-0.0.5.dist-info/LICENSE
cariuska-0.0.5.dist-info/METADATA
cariuska-0.0.5.dist-info/WHEEL
cariuska-0.0.5.dist-info/top_level.txt
cariuska-0.0.5.dist-info/RECORD
