Metadata-Version: 2.1
Name: cariuska
Version: 0.0.5
Summary: Cariuska Package
Author-email: Thiago Cariuska <tcariuska@gmail.com>
Project-URL: Homepage, https://github.com/cariuska/cariuska_pkg
Classifier: Programming Language :: Python :: 3
Classifier: License :: OSI Approved :: MIT License
Classifier: Operating System :: OS Independent
Requires-Python: >=3.8
License-File: LICENSE
